batterystaple-0.1.0dev1.dist-info/DESCRIPTION.rst
batterystaple-0.1.0dev1.dist-info/WHEEL
batterystaple-0.1.0dev1.dist-info/RECORD
batterystaple-0.1.0dev1.dist-info/metadata.json
batterystaple-0.1.0dev1.dist-info/METADATA
batterystaple-0.1.0dev1.dist-info/top_level.txt
batterystaple/__init__.py
batterystaple/resources/word_list_en.txt
