Metadata-Version: 2.0
Name: batterystaple
Version: 0.1.0dev1
Summary: Small library for generating XKCD style passphrases
Home-page: https://github.com/chucksmash/batterystaple
Author: Chuck Bassett
Author-email: iamchuckb@gmail.com
License: MIT
Keywords: passwords passphrases
Platform: UNKNOWN
Classifier: Development Status :: 3 - Alpha
Classifier: Environment :: Console
Classifier: Intended Audience :: Developers
Classifier: License :: OSI Approved :: MIT License
Classifier: Natural Language :: English
Classifier: Operating System :: Mac OS :: MaxOS X
Classifier: Operating System :: Microsoft :: Windows
Classifier: Operating System :: POSIX
Classifier: Programming Language :: Python :: 2.7
